exit_stack_container/__init__.py
exit_stack_container/defaults.py
exit_stack_container/dependency.py
exit_stack_container/exceptions.py
exit_stack_container/models.py
exit_stack_container/on_exit.py
exit_stack_container/py.typed
exit_stack_container/types.py
exit_stack_container/container/__init__.py
exit_stack_container/container/async_container.py
exit_stack_container/container/container.py
exit_stack_container/container/helpers.py
exit_stack_container-0.1.3.dist-info/METADATA
exit_stack_container-0.1.3.dist-info/WHEEL
exit_stack_container-0.1.3.dist-info/licenses/LICENSE
exit_stack_container-0.1.3.dist-info/RECORD
