Metadata-Version: 2.4
Name: exit-stack-container
Version: 0.1.3
Summary: Async lifecycle management with declarative dependency injection
Project-URL: Repository, https://github.com/qqqoid/exit-stack-container
Project-URL: Issues, https://github.com/qqqoid/exit-stack-container/issues
Author-email: "Salavat D. Samigoullin" <qqq@oid.su>
License: MIT
License-File: LICENSE
Keywords: async,asyncio,dependency-injection,di-container,lifecycle
Classifier: Development Status :: 3 - Alpha
Classifier: Framework :: AsyncIO
Classifier: Intended Audience :: Developers
Classifier: License :: OSI Approved :: MIT License
Classifier: Programming Language :: Python :: 3
Classifier: Programming Language :: Python :: 3.13
Classifier: Topic :: Software Development :: Libraries :: Python Modules
Classifier: Typing :: Typed
Requires-Python: >=3.13
Requires-Dist: msgspec-settings>=0.1.0
Requires-Dist: msgspec>=0.20.0
Provides-Extra: dev
Requires-Dist: ipykernel>=6.29.5; extra == 'dev'
Requires-Dist: ipython>=8.18.0; extra == 'dev'
Requires-Dist: ipywidgets>=8.1.0; extra == 'dev'
